setup.py
gharib_probability/Binomialdistribution.py
gharib_probability/Gaussiandistribution.py
gharib_probability/Generaldistribution.py
gharib_probability/__init__.py
gharib_probability.egg-info/PKG-INFO
gharib_probability.egg-info/SOURCES.txt
gharib_probability.egg-info/dependency_links.txt
gharib_probability.egg-info/not-zip-safe
gharib_probability.egg-info/top_level.txt