Metadata-Version: 1.0
Name: gharib-probability
Version: 0.1
Summary: Gaussian and Binomial distributions
Home-page: UNKNOWN
Author: Ahmed Gharib
Author-email: a.gharib89@yahoo.com
License: UNKNOWN
Platform: UNKNOWN
